perm.py
selfLineOverwriter-18.10.17.dist-info/DESCRIPTION.rst
selfLineOverwriter-18.10.17.dist-info/METADATA
selfLineOverwriter-18.10.17.dist-info/RECORD
selfLineOverwriter-18.10.17.dist-info/WHEEL
selfLineOverwriter-18.10.17.dist-info/metadata.json
selfLineOverwriter-18.10.17.dist-info/top_level.txt
